openinference/instrumentation/strands_agents/__init__.py
openinference/instrumentation/strands_agents/package.py
openinference/instrumentation/strands_agents/processor.py
openinference/instrumentation/strands_agents/semantic_conventions.py
openinference_instrumentation_strands_agents-0.1.0.dist-info/METADATA
openinference_instrumentation_strands_agents-0.1.0.dist-info/WHEEL
openinference_instrumentation_strands_agents-0.1.0.dist-info/licenses/LICENSE
openinference_instrumentation_strands_agents-0.1.0.dist-info/RECORD
