Metadata-Version: 2.4
Name: openinference-instrumentation-strands-agents
Version: 0.1.0
Summary: OpenInference span processor for Strands Agents - transforms native OpenTelemetry spans to OpenInference format
Project-URL: Homepage, https://github.com/Arize-ai/openinference/tree/main/python/instrumentation/openinference-instrumentation-strands-agents
Author-email: OpenInference Authors <oss@arize.com>
License-Expression: Apache-2.0
License-File: LICENSE
Classifier: Development Status :: 5 - Production/Stable
Classifier: Intended Audience :: Developers
Classifier: License :: OSI Approved :: Apache Software License
Classifier: Programming Language :: Python
Classifier: Programming Language :: Python :: 3
Classifier: Programming Language :: Python :: 3.10
Classifier: Programming Language :: Python :: 3.11
Classifier: Programming Language :: Python :: 3.12
Classifier: Programming Language :: Python :: 3.13
Classifier: Programming Language :: Python :: 3.14
Requires-Python: <3.15,>=3.10
Requires-Dist: openinference-semantic-conventions>=0.1.17
Requires-Dist: opentelemetry-api>=1.39.0
Requires-Dist: opentelemetry-sdk>=1.39.0
Requires-Dist: opentelemetry-semantic-conventions>=0.52b0
Requires-Dist: typing-extensions
Provides-Extra: instruments
Requires-Dist: strands-agents>=1.19.0; extra == 'instruments'
Provides-Extra: test
Requires-Dist: openai; extra == 'test'
Requires-Dist: pytest; extra == 'test'
Requires-Dist: pytest-asyncio; extra == 'test'
Requires-Dist: strands-agents>=1.19.0; extra == 'test'
